{
	"questsIds": [
		{
			"guid": "6064629449786523727",
			"typeId": "1091110035",
			"name": "None"
		}
	],
	"activePopulationSetsIds": [
		{
			"guid": "6064630270761778475",
			"typeId": "5111005",
			"name": "None"
		},
		{
			"guid": "6064630270761779174",
			"typeId": "5111005",
			"name": "None"
		},
		{
			"guid": "6064630270761778715",
			"typeId": "5111005",
			"name": "None"
		},
		{
			"guid": "6064630270761778464",
			"typeId": "5111005",
			"name": "None"
		},
		{
			"guid": "6064630270761781316",
			"typeId": "5111005",
			"name": "None"
		},
		{
			"guid": "6064630270761781708",
			"typeId": "5111005",
			"name": "None"
		},
		{
			"guid": "6064630270761780081",
			"typeId": "5111005",
			"name": "None"
		},
		{
			"guid": "6064630270761780995",
			"typeId": "5111005",
			"name": "None"
		},
		{
			"guid": "6064630270761781616",
			"typeId": "5111005",
			"name": "None"
		},
		{
			"guid": "6064630270761778705",
			"typeId": "5111005",
			"name": "None"
		},
		{
			"guid": "6064630270761779001",
			"typeId": "5111005",
			"name": "None"
		},
		{
			"guid": "6064630270761780074",
			"typeId": "5111005",
			"name": "None"
		}
	],
	"phaseSpawnLocationsIds": [
		{
			"guid": "6064630445775192289",
			"typeId": "1091110237",
			"name": "None"
		},
		{
			"guid": "6064630445775192290",
			"typeId": "1091110237",
			"name": "None"
		},
		{
			"guid": "6064630445775192291",
			"typeId": "1091110237",
			"name": "None"
		},
		{
			"guid": "6064630445775192292",
			"typeId": "1091110237",
			"name": "None"
		},
		{
			"guid": "6064630445775192293",
			"typeId": "1091110237",
			"name": "None"
		},
		{
			"guid": "6064630445775192294",
			"typeId": "1091110237",
			"name": "None"
		},
		{
			"guid": "6064630445775192295",
			"typeId": "1091110237",
			"name": "None"
		},
		{
			"guid": "6064630445775192296",
			"typeId": "1091110237",
			"name": "None"
		},
		{
			"guid": "6064630445775192297",
			"typeId": "1091110237",
			"name": "None"
		},
		{
			"guid": "6064630445775192298",
			"typeId": "1091110237",
			"name": "None"
		},
		{
			"guid": "6064630445775192299",
			"typeId": "1091110237",
			"name": "None"
		},
		{
			"guid": "6064630445775192300",
			"typeId": "1091110237",
			"name": "None"
		}
	],
	"spawnLocationsIds": [
		{
			"guid": "6064631091671794036",
			"typeId": "5127371160",
			"name": "None"
		},
		{
			"guid": "6064631091671794037",
			"typeId": "5127371160",
			"name": "None"
		},
		{
			"guid": "6064631091671794038",
			"typeId": "5127371160",
			"name": "None"
		},
		{
			"guid": "6064631091671794039",
			"typeId": "5127371160",
			"name": "None"
		},
		{
			"guid": "6064631091671794040",
			"typeId": "5127371160",
			"name": "None"
		},
		{
			"guid": "6064631091671794041",
			"typeId": "5127371160",
			"name": "None"
		},
		{
			"guid": "6064631091671794042",
			"typeId": "5127371160",
			"name": "None"
		},
		{
			"guid": "6064631091671794043",
			"typeId": "5127371160",
			"name": "None"
		},
		{
			"guid": "6064631091671794044",
			"typeId": "5127371160",
			"name": "None"
		},
		{
			"guid": "6064631091671794045",
			"typeId": "5127371160",
			"name": "None"
		},
		{
			"guid": "6064631091671794046",
			"typeId": "5127371160",
			"name": "None"
		},
		{
			"guid": "6064631091671794047",
			"typeId": "5127371160",
			"name": "None"
		}
	],
	"interactVolumesIds": [],
	"cannonizeOnEarlyTermination": false,
	"cannonizeOnNormalAdvancement": false,
	"phaseName": "NSLOCTEXT(\"\", \"4B23ECF54D26C1D0F62A89927AACEFD2\", \"The Rivals\")",
	"transitionsIds": [
		{
			"guid": "6064629444287397891",
			"typeId": "1091110034",
			"name": "None"
		}
	],
	"advancePhaseByTime": true,
	"advancementTime": 259200,
	"canAdvance":
	{
		"expression": ""
	},
	"timeAdvancePhaseId":
	{
		"guid": "0",
		"typeId": "1091110034",
		"name": "None"
	},
	"leaveSequenceId":
	{
		"guid": "0",
		"typeId": "1091110043",
		"name": "None"
	},
	"leaveSequenceWorldTransform":
	{
		"rotation":
		{
			"x": 0,
			"y": 0,
			"z": 0,
			"w": 1
		},
		"translation":
		{
			"x": 0,
			"y": 0,
			"z": 0
		},
		"scale3D":
		{
			"x": 1,
			"y": 1,
			"z": 1
		}
	},
	"enterSequenceId":
	{
		"guid": "0",
		"typeId": "1091110043",
		"name": "None"
	},
	"enterSequenceWorldTransform":
	{
		"rotation":
		{
			"x": 0,
			"y": 0,
			"z": 0,
			"w": 1
		},
		"translation":
		{
			"x": 0,
			"y": 0,
			"z": 0
		},
		"scale3D":
		{
			"x": 1,
			"y": 1,
			"z": 1
		}
	},
	"guid": "6064629444284317698",
	"name": "MIP_0020_KOC_Phase02",
	"typeId": "1091110034"
}