{
	"stats":
	{
		"108986356618873":
		{
			"commonMin": 92610,
			"commonMax": 113050,
			"uncommonMin": 118160,
			"uncommonMax": 164150,
			"rareMin": 169260,
			"rareMax": 240800,
			"heroicMin": 245910,
			"heroicMax": 343000,
			"epicMin": 348110,
			"epicMax": 445200,
			"legendaryMin": 450310,
			"legendaryMax": 598500,
			"artifactMin": 0,
			"artifactMax": 0
		},
		"109183607068294":
		{
			"commonMin": 2410,
			"commonMax": 2940,
			"uncommonMin": 3080,
			"uncommonMax": 4270,
			"rareMin": 4410,
			"rareMax": 6270,
			"heroicMin": 6400,
			"heroicMax": 8920,
			"epicMin": 9060,
			"epicMax": 11580,
			"legendaryMin": 11710,
			"legendaryMax": 15570,
			"artifactMin": 0,
			"artifactMax": 0
		},
		"109183607133840":
		{
			"commonMin": 3150,
			"commonMax": 3850,
			"uncommonMin": 4020,
			"uncommonMax": 5590,
			"rareMin": 5760,
			"rareMax": 8190,
			"heroicMin": 8370,
			"heroicMax": 11670,
			"epicMin": 11840,
			"epicMax": 15140,
			"legendaryMin": 15320,
			"legendaryMax": 20350,
			"artifactMin": 0,
			"artifactMax": 0
		},
		"6064629976272535552":
		{
			"commonMin": 3,
			"commonMax": 3,
			"uncommonMin": 3,
			"uncommonMax": 3,
			"rareMin": 3,
			"rareMax": 3,
			"heroicMin": 3,
			"heroicMax": 3,
			"epicMin": 4,
			"epicMax": 4,
			"legendaryMin": 4,
			"legendaryMax": 4,
			"artifactMin": 0,
			"artifactMax": 0
		}
	},
	"statArchetype":
	{
		"108986356618873": "Primary",
		"109183607068294": "Primary",
		"109183607133840": "Primary",
		"6064629976272535552": "Core"
	},
	"guid": "6064632265060804146",
	"name": "Caravan_Carriage_IronStatBlock",
	"typeId": "10911100031237784"
}