{
	"prerequisitesIds": [],
	"levelsIds":
	{
		"3":
		{
			"guid": "6064629466537459746",
			"typeId": "7823458",
			"name": "None"
		},
		"4":
		{
			"guid": "6064629466537656355",
			"typeId": "7823458",
			"name": "None"
		},
		"5":
		{
			"guid": "6064629466537852964",
			"typeId": "7823458",
			"name": "None"
		},
		"6":
		{
			"guid": "6064629466537984037",
			"typeId": "7823458",
			"name": "None"
		}
	},
	"buildingAssetSetId":
	{
		"guid": "0",
		"typeId": "1323521346",
		"name": "None"
	},
	"nodeConstructionCostId":
	{
		"guid": "0",
		"typeId": "7823457",
		"name": "None"
	},
	"maintenanceCostId":
	{
		"guid": "0",
		"typeId": "7823457",
		"name": "None"
	},
	"playerConstructionCostId":
	{
		"guid": "0",
		"typeId": "7823457",
		"name": "None"
	},
	"repairCostId":
	{
		"guid": "0",
		"typeId": "7823457",
		"name": "None"
	},
	"disarrayRepairCostId":
	{
		"guid": "0",
		"typeId": "7823457",
		"name": "None"
	},
	"disarrayDebuffId":
	{
		"guid": "0",
		"typeId": "30316002",
		"name": "None"
	},
	"dEPRECATED_ExpansionsIds": [],
	"serviceBuildingType": "Vocational",
	"housingPropertyTiersIds": [],
	"icon": "/Game/UI/Icons/Nodes/Buildings/Stables/TUI_Icon_Stables.TUI_Icon_Stables",
	"mapIconVisualId":
	{
		"guid": "0",
		"typeId": "949952112329",
		"name": "None"
	},
	"buildingName": "Stables",
	"buildingDescription": "The Stables services players mount and pet needs in terms of storage, upgrade, and training.",
	"buildingServices": [],
	"buildingServiceDescriptions": [],
	"bDisplayInBuildingManager": true,
	"constructionPhaseDuration":
	{
		"duration": "86400000"
	},
	"buildingContributionPhasesId":
	{
		"guid": "6064629841000792168",
		"typeId": "1091110047",
		"name": "None"
	},
	"dEPRECATED_CapabilitiesIds": [],
	"dEPRECATED_NodeEffectId":
	{
		"guid": "0",
		"typeId": "9127426",
		"name": "None"
	},
	"localeOriginId":
	{
		"guid": "0",
		"typeId": "421003",
		"name": "None"
	},
	"nodeModificationsIds": [],
	"expansionSkillTreeId":
	{
		"guid": "0",
		"typeId": "30316003",
		"name": "None"
	},
	"repairStateDurationModifier":
	{
		"expression": ""
	},
	"demolitionStateDurationModifier":
	{
		"expression": ""
	},
	"voteResultDuration":
	{
		"expression": ""
	},
	"guid": "6064629467056900107",
	"name": "NONA2Construction_Active_Stables_Building",
	"typeId": "7823463"
}