{
	"waypointLocations": [
		{
			"x": -960705.30779481435,
			"y": 394261.85762487608,
			"z": 16161.420258957993
		},
		{
			"x": -960455.30779481435,
			"y": 393291.85762487608,
			"z": 16161.420258957993
		},
		{
			"x": -960455.30779481435,
			"y": 391551.85762487608,
			"z": 16161.420258957993
		},
		{
			"x": -960455.30779481435,
			"y": 389151.85762487608,
			"z": 16161.420258957993
		},
		{
			"x": -957905.30779481435,
			"y": 389151.85762487608,
			"z": 16433.449929673327
		},
		{
			"x": -957905.30779481435,
			"y": 389961.85762487608,
			"z": 16433.449929673327
		},
		{
			"x": -956375.30779481435,
			"y": 389961.85762487608,
			"z": 16433.449929673327
		},
		{
			"x": -956375.30779481435,
			"y": 393331.85762487608,
			"z": 16433.449929673327
		},
		{
			"x": -957725.30779481435,
			"y": 394041.85762487608,
			"z": 16433.449929673327
		},
		{
			"x": -960675.30779481435,
			"y": 394041.85762487608,
			"z": 16119.54508348192
		}
	],
	"relativeToCityNode": false,
	"looping": true,
	"startRouteClosestPoint": true,
	"pathingSet": "RVR_Halcyon_WestHuntingGrounds",
	"pathActorTransform":
	{
		"rotation":
		{
			"x": 0,
			"y": 0,
			"z": 0,
			"w": 1
		},
		"translation":
		{
			"x": -960705.30779481435,
			"y": 394261.85762487608,
			"z": 16161.420258957993
		},
		"scale3D":
		{
			"x": 1,
			"y": 1,
			"z": 1
		}
	},
	"splineCurves":
	{
		"position":
		{
			"points": [],
			"bIsLooped": false,
			"loopKeyOffset": 0
		},
		"rotation":
		{
			"points": [],
			"bIsLooped": false,
			"loopKeyOffset": 0
		},
		"scale":
		{
			"points": [],
			"bIsLooped": false,
			"loopKeyOffset": 0
		},
		"reparamTable":
		{
			"points": [],
			"bIsLooped": false,
			"loopKeyOffset": 0
		},
		"version": 4294967295
	},
	"guid": "6064631279374172165",
	"name": "Halcyon_WestHuntingGrounds_Goblin_Shaman_Patrol_5",
	"typeId": "250007"
}