{
	"displayName": "NSLOCTEXT(\"\", \"45A9C7824A66342AC47A008D75BC2536\", \"Lumberjacking Rarity Rating\")",
	"description": "NSLOCTEXT(\"[D20C99C24B2FABB4DC05E3BF1EE067C5]\", \"066F10C24F878E3699CB219FBC81D49B\", \"Increases the chance to get rarer Lumberjacking Resources while gathering with all Lumberjacking tools\")",
	"bHidden": false,
	"gameplayType": "Type_Artisanship",
	"bHasWaterfallStatsUI": false,
	"waterfallStatsUIIds": [],
	"bDisplayAsPercentage": false,
	"statType": "Type_Float",
	"bClampStatFinalValue": false,
	"bMultiplyStatMods": false,
	"bMultiplyCompliment": false,
	"base":
	{
		"expression": ""
	},
	"waterfallStatsBaseIds": [],
	"valueMin":
	{
		"expression": "0"
	},
	"waterfallStatsMinIds": [],
	"valueMax":
	{
		"expression": "99999"
	},
	"waterfallStatsMaxIds": [],
	"regenRate":
	{
		"expression": ""
	},
	"waterfallStatsRegenIds": [],
	"bRegenWhileDead": false,
	"onSpawn": "Reset_None",
	"onDeath": "Reset_None",
	"onRevive": "Reset_None",
	"bPersistValue": false,
	"replication": 1,
	"shieldStatId":
	{
		"guid": "0",
		"typeId": "10516612381411111",
		"name": "None"
	},
	"guid": "6064629302956327332",
	"name": "Artisan_Gathering_Lumberjacking_Rarity_Rating",
	"typeId": "10516612381411111"
}