{
	"abilityIdId":
	{
		"guid": "107933095384696",
		"typeId": "30316001",
		"name": "Prototype_Fighter_Whirlwind"
	},
	"effectIdId":
	{
		"guid": "0",
		"typeId": "30316002",
		"name": "None"
	},
	"guildEffectIdId":
	{
		"guid": "0",
		"typeId": "30311337",
		"name": "None"
	},
	"cost": 1,
	"expansionId":
	{
		"guid": "0",
		"typeId": "7823461",
		"name": "None"
	},
	"skillCost":
	{
		"skillPointCosts": [
			{
				"skillPointTypeId":
				{
					"guid": "6064631448935923712",
					"typeId": "981011400",
					"name": "None"
				},
				"quantity": 1
			}
		],
		"commodityCosts": [],
		"currencyCosts": []
	},
	"tooltipText": "Channeled ability: Deal $hit1$ to all enemies around the caster with each spin while channeled, increasing the spin rate the longer it is channeled. \r\n\r\nThe caster is immune to hard disabling effects while spinning.\r\n\r\nActivate the ability again to end channeling early.",
	"tooltipIcon": "/Game/UI/Icons/Archetypes/Fighter/Abilities/TUI_AbilityIcon_Whirlwind.TUI_AbilityIcon_Whirlwind",
	"guid": "108073400227448",
	"name": "Fighter_Whirlwind",
	"typeId": "981011101"
}