{
	"expression":
	{
		"expression": ""
	},
	"tickInterval": 5,
	"maxActivationCount": 1,
	"objectivesIds": [
		{
			"guid": "6064631012186259516",
			"typeId": "23095130",
			"name": "None"
		}
	],
	"triggersIds": [
		{
			"guid": "6064631279707685076",
			"typeId": "23095135",
			"name": "None"
		},
		{
			"guid": "6064631012186259517",
			"typeId": "23095135",
			"name": "None"
		},
		{
			"guid": "6064631012186259518",
			"typeId": "23095135",
			"name": "None"
		}
	],
	"flowEditorNodeLocation":
	{
		"x": 0,
		"y": 0,
		"z": 0
	},
	"routePins": [],
	"guid": "6064631012186259515",
	"name": "ProgE_RVR_Event_0004_ColossusCrater_Phase2_Rewards_TimerObjective",
	"typeId": "23095129"
}