{
	"curve":
	{
		"externalCurve": "None",
		"editorCurveData":
		{
			"keys": [
				{
					"interpMode": "RCIM_Linear",
					"tangentMode": "RCTM_Auto",
					"tangentWeightMode": "RCTWM_WeightedNone",
					"time": 1,
					"value": 100,
					"arriveTangent": 0,
					"arriveTangentWeight": 0,
					"leaveTangent": 0,
					"leaveTangentWeight": 0
				},
				{
					"interpMode": "RCIM_Linear",
					"tangentMode": "RCTM_Auto",
					"tangentWeightMode": "RCTWM_WeightedNone",
					"time": 2,
					"value": 150,
					"arriveTangent": 0,
					"arriveTangentWeight": 0,
					"leaveTangent": 0,
					"leaveTangentWeight": 0
				},
				{
					"interpMode": "RCIM_Linear",
					"tangentMode": "RCTM_Auto",
					"tangentWeightMode": "RCTWM_WeightedNone",
					"time": 3,
					"value": 213,
					"arriveTangent": 0,
					"arriveTangentWeight": 0,
					"leaveTangent": 0,
					"leaveTangentWeight": 0
				},
				{
					"interpMode": "RCIM_Linear",
					"tangentMode": "RCTM_Auto",
					"tangentWeightMode": "RCTWM_WeightedNone",
					"time": 4,
					"value": 286,
					"arriveTangent": 0,
					"arriveTangentWeight": 0,
					"leaveTangent": 0,
					"leaveTangentWeight": 0
				},
				{
					"interpMode": "RCIM_Linear",
					"tangentMode": "RCTM_Auto",
					"tangentWeightMode": "RCTWM_WeightedNone",
					"time": 5,
					"value": 368,
					"arriveTangent": 0,
					"arriveTangentWeight": 0,
					"leaveTangent": 0,
					"leaveTangentWeight": 0
				},
				{
					"interpMode": "RCIM_Linear",
					"tangentMode": "RCTM_Auto",
					"tangentWeightMode": "RCTWM_WeightedNone",
					"time": 6,
					"value": 459,
					"arriveTangent": 0,
					"arriveTangentWeight": 0,
					"leaveTangent": 0,
					"leaveTangentWeight": 0
				},
				{
					"interpMode": "RCIM_Linear",
					"tangentMode": "RCTM_Auto",
					"tangentWeightMode": "RCTWM_WeightedNone",
					"time": 7,
					"value": 559,
					"arriveTangent": 0,
					"arriveTangentWeight": 0,
					"leaveTangent": 0,
					"leaveTangentWeight": 0
				},
				{
					"interpMode": "RCIM_Linear",
					"tangentMode": "RCTM_Auto",
					"tangentWeightMode": "RCTWM_WeightedNone",
					"time": 8,
					"value": 668,
					"arriveTangent": 0,
					"arriveTangentWeight": 0,
					"leaveTangent": 0,
					"leaveTangentWeight": 0
				},
				{
					"interpMode": "RCIM_Linear",
					"tangentMode": "RCTM_Auto",
					"tangentWeightMode": "RCTWM_WeightedNone",
					"time": 9,
					"value": 785,
					"arriveTangent": 0,
					"arriveTangentWeight": 0,
					"leaveTangent": 0,
					"leaveTangentWeight": 0
				},
				{
					"interpMode": "RCIM_Linear",
					"tangentMode": "RCTM_Auto",
					"tangentWeightMode": "RCTWM_WeightedNone",
					"time": 10,
					"value": 911,
					"arriveTangent": 0,
					"arriveTangentWeight": 0,
					"leaveTangent": 0,
					"leaveTangentWeight": 0
				},
				{
					"interpMode": "RCIM_Linear",
					"tangentMode": "RCTM_Auto",
					"tangentWeightMode": "RCTWM_WeightedNone",
					"time": 11,
					"value": 1046,
					"arriveTangent": 0,
					"arriveTangentWeight": 0,
					"leaveTangent": 0,
					"leaveTangentWeight": 0
				},
				{
					"interpMode": "RCIM_Linear",
					"tangentMode": "RCTM_Auto",
					"tangentWeightMode": "RCTWM_WeightedNone",
					"time": 12,
					"value": 1190,
					"arriveTangent": 0,
					"arriveTangentWeight": 0,
					"leaveTangent": 0,
					"leaveTangentWeight": 0
				},
				{
					"interpMode": "RCIM_Linear",
					"tangentMode": "RCTM_Auto",
					"tangentWeightMode": "RCTWM_WeightedNone",
					"time": 13,
					"value": 1342,
					"arriveTangent": 0,
					"arriveTangentWeight": 0,
					"leaveTangent": 0,
					"leaveTangentWeight": 0
				},
				{
					"interpMode": "RCIM_Linear",
					"tangentMode": "RCTM_Auto",
					"tangentWeightMode": "RCTWM_WeightedNone",
					"time": 14,
					"value": 1505,
					"arriveTangent": 0,
					"arriveTangentWeight": 0,
					"leaveTangent": 0,
					"leaveTangentWeight": 0
				},
				{
					"interpMode": "RCIM_Linear",
					"tangentMode": "RCTM_Auto",
					"tangentWeightMode": "RCTWM_WeightedNone",
					"time": 15,
					"value": 1676,
					"arriveTangent": 0,
					"arriveTangentWeight": 0,
					"leaveTangent": 0,
					"leaveTangentWeight": 0
				},
				{
					"interpMode": "RCIM_Linear",
					"tangentMode": "RCTM_Auto",
					"tangentWeightMode": "RCTWM_WeightedNone",
					"time": 16,
					"value": 1856,
					"arriveTangent": 0,
					"arriveTangentWeight": 0,
					"leaveTangent": 0,
					"leaveTangentWeight": 0
				},
				{
					"interpMode": "RCIM_Linear",
					"tangentMode": "RCTM_Auto",
					"tangentWeightMode": "RCTWM_WeightedNone",
					"time": 17,
					"value": 2046,
					"arriveTangent": 0,
					"arriveTangentWeight": 0,
					"leaveTangent": 0,
					"leaveTangentWeight": 0
				},
				{
					"interpMode": "RCIM_Linear",
					"tangentMode": "RCTM_Auto",
					"tangentWeightMode": "RCTWM_WeightedNone",
					"time": 18,
					"value": 2245,
					"arriveTangent": 0,
					"arriveTangentWeight": 0,
					"leaveTangent": 0,
					"leaveTangentWeight": 0
				},
				{
					"interpMode": "RCIM_Linear",
					"tangentMode": "RCTM_Auto",
					"tangentWeightMode": "RCTWM_WeightedNone",
					"time": 19,
					"value": 2454,
					"arriveTangent": 0,
					"arriveTangentWeight": 0,
					"leaveTangent": 0,
					"leaveTangentWeight": 0
				},
				{
					"interpMode": "RCIM_Linear",
					"tangentMode": "RCTM_Auto",
					"tangentWeightMode": "RCTWM_WeightedNone",
					"time": 20,
					"value": 2672,
					"arriveTangent": 0,
					"arriveTangentWeight": 0,
					"leaveTangent": 0,
					"leaveTangentWeight": 0
				},
				{
					"interpMode": "RCIM_Linear",
					"tangentMode": "RCTM_Auto",
					"tangentWeightMode": "RCTWM_WeightedNone",
					"time": 21,
					"value": 2900,
					"arriveTangent": 0,
					"arriveTangentWeight": 0,
					"leaveTangent": 0,
					"leaveTangentWeight": 0
				},
				{
					"interpMode": "RCIM_Linear",
					"tangentMode": "RCTM_Auto",
					"tangentWeightMode": "RCTWM_WeightedNone",
					"time": 22,
					"value": 3137,
					"arriveTangent": 0,
					"arriveTangentWeight": 0,
					"leaveTangent": 0,
					"leaveTangentWeight": 0
				},
				{
					"interpMode": "RCIM_Linear",
					"tangentMode": "RCTM_Auto",
					"tangentWeightMode": "RCTWM_WeightedNone",
					"time": 23,
					"value": 3384,
					"arriveTangent": 0,
					"arriveTangentWeight": 0,
					"leaveTangent": 0,
					"leaveTangentWeight": 0
				},
				{
					"interpMode": "RCIM_Linear",
					"tangentMode": "RCTM_Auto",
					"tangentWeightMode": "RCTWM_WeightedNone",
					"time": 24,
					"value": 3641,
					"arriveTangent": 0,
					"arriveTangentWeight": 0,
					"leaveTangent": 0,
					"leaveTangentWeight": 0
				},
				{
					"interpMode": "RCIM_Linear",
					"tangentMode": "RCTM_Auto",
					"tangentWeightMode": "RCTWM_WeightedNone",
					"time": 25,
					"value": 3907,
					"arriveTangent": 0,
					"arriveTangentWeight": 0,
					"leaveTangent": 0,
					"leaveTangentWeight": 0
				},
				{
					"interpMode": "RCIM_Linear",
					"tangentMode": "RCTM_Auto",
					"tangentWeightMode": "RCTWM_WeightedNone",
					"time": 26,
					"value": 4183,
					"arriveTangent": 0,
					"arriveTangentWeight": 0,
					"leaveTangent": 0,
					"leaveTangentWeight": 0
				},
				{
					"interpMode": "RCIM_Linear",
					"tangentMode": "RCTM_Auto",
					"tangentWeightMode": "RCTWM_WeightedNone",
					"time": 27,
					"value": 4468,
					"arriveTangent": 0,
					"arriveTangentWeight": 0,
					"leaveTangent": 0,
					"leaveTangentWeight": 0
				},
				{
					"interpMode": "RCIM_Linear",
					"tangentMode": "RCTM_Auto",
					"tangentWeightMode": "RCTWM_WeightedNone",
					"time": 28,
					"value": 4763,
					"arriveTangent": 0,
					"arriveTangentWeight": 0,
					"leaveTangent": 0,
					"leaveTangentWeight": 0
				},
				{
					"interpMode": "RCIM_Linear",
					"tangentMode": "RCTM_Auto",
					"tangentWeightMode": "RCTWM_WeightedNone",
					"time": 29,
					"value": 5067,
					"arriveTangent": 0,
					"arriveTangentWeight": 0,
					"leaveTangent": 0,
					"leaveTangentWeight": 0
				},
				{
					"interpMode": "RCIM_Linear",
					"tangentMode": "RCTM_Auto",
					"tangentWeightMode": "RCTWM_WeightedNone",
					"time": 30,
					"value": 5381,
					"arriveTangent": 0,
					"arriveTangentWeight": 0,
					"leaveTangent": 0,
					"leaveTangentWeight": 0
				},
				{
					"interpMode": "RCIM_Linear",
					"tangentMode": "RCTM_Auto",
					"tangentWeightMode": "RCTWM_WeightedNone",
					"time": 31,
					"value": 5704,
					"arriveTangent": 0,
					"arriveTangentWeight": 0,
					"leaveTangent": 0,
					"leaveTangentWeight": 0
				},
				{
					"interpMode": "RCIM_Linear",
					"tangentMode": "RCTM_Auto",
					"tangentWeightMode": "RCTWM_WeightedNone",
					"time": 32,
					"value": 6036,
					"arriveTangent": 0,
					"arriveTangentWeight": 0,
					"leaveTangent": 0,
					"leaveTangentWeight": 0
				},
				{
					"interpMode": "RCIM_Linear",
					"tangentMode": "RCTM_Auto",
					"tangentWeightMode": "RCTWM_WeightedNone",
					"time": 33,
					"value": 6379,
					"arriveTangent": 0,
					"arriveTangentWeight": 0,
					"leaveTangent": 0,
					"leaveTangentWeight": 0
				},
				{
					"interpMode": "RCIM_Linear",
					"tangentMode": "RCTM_Auto",
					"tangentWeightMode": "RCTWM_WeightedNone",
					"time": 34,
					"value": 6729,
					"arriveTangent": 0,
					"arriveTangentWeight": 0,
					"leaveTangent": 0,
					"leaveTangentWeight": 0
				},
				{
					"interpMode": "RCIM_Linear",
					"tangentMode": "RCTM_Auto",
					"tangentWeightMode": "RCTWM_WeightedNone",
					"time": 35,
					"value": 7090,
					"arriveTangent": 0,
					"arriveTangentWeight": 0,
					"leaveTangent": 0,
					"leaveTangentWeight": 0
				},
				{
					"interpMode": "RCIM_Linear",
					"tangentMode": "RCTM_Auto",
					"tangentWeightMode": "RCTWM_WeightedNone",
					"time": 36,
					"value": 7459,
					"arriveTangent": 0,
					"arriveTangentWeight": 0,
					"leaveTangent": 0,
					"leaveTangentWeight": 0
				},
				{
					"interpMode": "RCIM_Linear",
					"tangentMode": "RCTM_Auto",
					"tangentWeightMode": "RCTWM_WeightedNone",
					"time": 37,
					"value": 7837,
					"arriveTangent": 0,
					"arriveTangentWeight": 0,
					"leaveTangent": 0,
					"leaveTangentWeight": 0
				},
				{
					"interpMode": "RCIM_Linear",
					"tangentMode": "RCTM_Auto",
					"tangentWeightMode": "RCTWM_WeightedNone",
					"time": 38,
					"value": 8224,
					"arriveTangent": 0,
					"arriveTangentWeight": 0,
					"leaveTangent": 0,
					"leaveTangentWeight": 0
				},
				{
					"interpMode": "RCIM_Linear",
					"tangentMode": "RCTM_Auto",
					"tangentWeightMode": "RCTWM_WeightedNone",
					"time": 39,
					"value": 8620,
					"arriveTangent": 0,
					"arriveTangentWeight": 0,
					"leaveTangent": 0,
					"leaveTangentWeight": 0
				},
				{
					"interpMode": "RCIM_Linear",
					"tangentMode": "RCTM_Auto",
					"tangentWeightMode": "RCTWM_WeightedNone",
					"time": 40,
					"value": 9025,
					"arriveTangent": 0,
					"arriveTangentWeight": 0,
					"leaveTangent": 0,
					"leaveTangentWeight": 0
				},
				{
					"interpMode": "RCIM_Linear",
					"tangentMode": "RCTM_Auto",
					"tangentWeightMode": "RCTWM_WeightedNone",
					"time": 41,
					"value": 9438,
					"arriveTangent": 0,
					"arriveTangentWeight": 0,
					"leaveTangent": 0,
					"leaveTangentWeight": 0
				},
				{
					"interpMode": "RCIM_Linear",
					"tangentMode": "RCTM_Auto",
					"tangentWeightMode": "RCTWM_WeightedNone",
					"time": 42,
					"value": 9860,
					"arriveTangent": 0,
					"arriveTangentWeight": 0,
					"leaveTangent": 0,
					"leaveTangentWeight": 0
				},
				{
					"interpMode": "RCIM_Linear",
					"tangentMode": "RCTM_Auto",
					"tangentWeightMode": "RCTWM_WeightedNone",
					"time": 43,
					"value": 10291,
					"arriveTangent": 0,
					"arriveTangentWeight": 0,
					"leaveTangent": 0,
					"leaveTangentWeight": 0
				},
				{
					"interpMode": "RCIM_Linear",
					"tangentMode": "RCTM_Auto",
					"tangentWeightMode": "RCTWM_WeightedNone",
					"time": 44,
					"value": 10731,
					"arriveTangent": 0,
					"arriveTangentWeight": 0,
					"leaveTangent": 0,
					"leaveTangentWeight": 0
				},
				{
					"interpMode": "RCIM_Linear",
					"tangentMode": "RCTM_Auto",
					"tangentWeightMode": "RCTWM_WeightedNone",
					"time": 45,
					"value": 11177,
					"arriveTangent": 0,
					"arriveTangentWeight": 0,
					"leaveTangent": 0,
					"leaveTangentWeight": 0
				},
				{
					"interpMode": "RCIM_Linear",
					"tangentMode": "RCTM_Auto",
					"tangentWeightMode": "RCTWM_WeightedNone",
					"time": 46,
					"value": 11633,
					"arriveTangent": 0,
					"arriveTangentWeight": 0,
					"leaveTangent": 0,
					"leaveTangentWeight": 0
				},
				{
					"interpMode": "RCIM_Linear",
					"tangentMode": "RCTM_Auto",
					"tangentWeightMode": "RCTWM_WeightedNone",
					"time": 47,
					"value": 12096,
					"arriveTangent": 0,
					"arriveTangentWeight": 0,
					"leaveTangent": 0,
					"leaveTangentWeight": 0
				},
				{
					"interpMode": "RCIM_Linear",
					"tangentMode": "RCTM_Auto",
					"tangentWeightMode": "RCTWM_WeightedNone",
					"time": 48,
					"value": 12568,
					"arriveTangent": 0,
					"arriveTangentWeight": 0,
					"leaveTangent": 0,
					"leaveTangentWeight": 0
				},
				{
					"interpMode": "RCIM_Linear",
					"tangentMode": "RCTM_Auto",
					"tangentWeightMode": "RCTWM_WeightedNone",
					"time": 49,
					"value": 13049,
					"arriveTangent": 0,
					"arriveTangentWeight": 0,
					"leaveTangent": 0,
					"leaveTangentWeight": 0
				},
				{
					"interpMode": "RCIM_Linear",
					"tangentMode": "RCTM_Auto",
					"tangentWeightMode": "RCTWM_WeightedNone",
					"time": 50,
					"value": 13536,
					"arriveTangent": 0,
					"arriveTangentWeight": 0,
					"leaveTangent": 0,
					"leaveTangentWeight": 0
				}
			],
			"defaultValue": 0,
			"preInfinityExtrap": "RCCE_Constant",
			"postInfinityExtrap": "RCCE_Constant",
			"keyHandlesToIndices":
			{
			}
		}
	},
	"guid": "6064632377010487296",
	"name": "Base_EHP",
	"typeId": "10516612381411114"
}