{
	"populationInstancesMap":
	{
		"1":
		{
			"location":
			{
				"x": -810535.46155281318,
				"y": 616861.21014585311,
				"z": 7962.9146633531509
			},
			"rotation":
			{
				"pitch": -0,
				"yaw": -170.0000014718095,
				"roll": 0
			},
			"bRandomRotation": false,
			"instanceId":
			{
				"guid": "6064630610576736285",
				"typeId": "5111011",
				"name": "None"
			}
		},
		"2":
		{
			"location":
			{
				"x": -810573.43898965488,
				"y": 617077.23317657434,
				"z": 7962.9147677857818
			},
			"rotation":
			{
				"pitch": 0,
				"yaw": 179.99999860565416,
				"roll": -0
			},
			"bRandomRotation": false,
			"instanceId":
			{
				"guid": "6064630610576736285",
				"typeId": "5111011",
				"name": "None"
			}
		},
		"3":
		{
			"location":
			{
				"x": -810627.13616060116,
				"y": 617300.69636081054,
				"z": 7952.914720926241
			},
			"rotation":
			{
				"pitch": 0,
				"yaw": 179.99999860565416,
				"roll": -0
			},
			"bRandomRotation": false,
			"instanceId":
			{
				"guid": "6064630610576736285",
				"typeId": "5111011",
				"name": "None"
			}
		},
		"4":
		{
			"location":
			{
				"x": -810679.03676743002,
				"y": 617506.25056229869,
				"z": 7952.9145568594195
			},
			"rotation":
			{
				"pitch": 0,
				"yaw": 179.99999860565416,
				"roll": -0
			},
			"bRandomRotation": false,
			"instanceId":
			{
				"guid": "6064630610576736285",
				"typeId": "5111011",
				"name": "None"
			}
		},
		"5":
		{
			"location":
			{
				"x": -810720.00296193839,
				"y": 617711.87542576168,
				"z": 7972.9146627332484
			},
			"rotation":
			{
				"pitch": -0,
				"yaw": -170.0000014718095,
				"roll": 0
			},
			"bRandomRotation": false,
			"instanceId":
			{
				"guid": "6064630610576736285",
				"typeId": "5111011",
				"name": "None"
			}
		},
		"6":
		{
			"location":
			{
				"x": -810774.23233420972,
				"y": 617917.46085279365,
				"z": 7972.579976889434
			},
			"rotation":
			{
				"pitch": -0,
				"yaw": -170.00000147180964,
				"roll": 0
			},
			"bRandomRotation": false,
			"instanceId":
			{
				"guid": "6064630610576736285",
				"typeId": "5111011",
				"name": "None"
			}
		},
		"7":
		{
			"location":
			{
				"x": -810828.22209858499,
				"y": 618117.26608744159,
				"z": 7962.32824500276
			},
			"rotation":
			{
				"pitch": -0,
				"yaw": -170.0000014718095,
				"roll": 0
			},
			"bRandomRotation": false,
			"instanceId":
			{
				"guid": "6064630610576736285",
				"typeId": "5111011",
				"name": "None"
			}
		},
		"8":
		{
			"location":
			{
				"x": -810687.13609185151,
				"y": 616636.37232374854,
				"z": 7952.9146790373925
			},
			"rotation":
			{
				"pitch": 0,
				"yaw": 99.99999922536351,
				"roll": -0
			},
			"bRandomRotation": false,
			"instanceId":
			{
				"guid": "6064630610608521253",
				"typeId": "5111011",
				"name": "None"
			}
		}
	},
	"filterOverrideId":
	{
		"guid": "0",
		"typeId": "5111003",
		"name": "None"
	},
	"populationAreaId":
	{
		"guid": "0",
		"typeId": "5171420",
		"name": "None"
	},
	"timedDespawnId":
	{
		"guid": "0",
		"typeId": "5882300",
		"name": "None"
	},
	"overrideActivationRange": 0,
	"gameplayTags":
	{
		"gameplayTags": [],
		"parentTags": []
	},
	"alignmentOverridesIds": [],
	"guid": "6064630610494488600",
	"name": "MAPS_0005A_FGG_Phase01_SettlerMilitiaRecruits",
	"typeId": "5111005"
}