{
	"populationInstancesMap":
	{
		"1":
		{
			"location":
			{
				"x": -37124.027690815099,
				"y": 35427.634874991956,
				"z": 102290.34245252576
			},
			"rotation":
			{
				"pitch": 0,
				"yaw": 0,
				"roll": 0
			},
			"bRandomRotation": false,
			"instanceId":
			{
				"guid": "6064632773030642413",
				"typeId": "5111011",
				"name": "None"
			}
		},
		"2":
		{
			"location":
			{
				"x": -36988.24082523433,
				"y": 36452.579662845703,
				"z": 106872.10417689147
			},
			"rotation":
			{
				"pitch": 0,
				"yaw": 0,
				"roll": 0
			},
			"bRandomRotation": false,
			"instanceId":
			{
				"guid": "6064632773036016366",
				"typeId": "5111011",
				"name": "None"
			}
		},
		"3":
		{
			"location":
			{
				"x": -37174.837270415854,
				"y": 37708.117558867554,
				"z": 121184.78596217235
			},
			"rotation":
			{
				"pitch": 0,
				"yaw": 0,
				"roll": 0
			},
			"bRandomRotation": false,
			"instanceId":
			{
				"guid": "6064632773040538351",
				"typeId": "5111011",
				"name": "None"
			}
		},
		"4":
		{
			"location":
			{
				"x": -21806.802025846206,
				"y": 45016.559300293215,
				"z": 149998.33458791682
			},
			"rotation":
			{
				"pitch": 0,
				"yaw": 0,
				"roll": 0
			},
			"bRandomRotation": false,
			"instanceId":
			{
				"guid": "6064632773043421936",
				"typeId": "5111011",
				"name": "None"
			}
		},
		"5":
		{
			"location":
			{
				"x": -106093.83480355825,
				"y": -218840.85381832405,
				"z": 13611.083527929308
			},
			"rotation":
			{
				"pitch": 0,
				"yaw": 0,
				"roll": 0
			},
			"bRandomRotation": false,
			"instanceId":
			{
				"guid": "6064632989490937860",
				"typeId": "5111011",
				"name": "None"
			}
		}
	},
	"filterOverrideId":
	{
		"guid": "0",
		"typeId": "5111003",
		"name": "None"
	},
	"populationAreaId":
	{
		"guid": "6064632772948525804",
		"typeId": "5171420",
		"name": "None"
	},
	"timedDespawnId":
	{
		"guid": "0",
		"typeId": "5882300",
		"name": "None"
	},
	"overrideActivationRange": 0,
	"gameplayTags":
	{
		"gameplayTags": [],
		"parentTags": []
	},
	"alignmentOverridesIds": [],
	"guid": "6064632772940989162",
	"name": "SAN_Azmaran_Wilderness_Northwest_AreaSpawners",
	"typeId": "5111005"
}