{
	"type": "Basic",
	"taskId":
	{
		"guid": "6064630882082095588",
		"typeId": "1095125186",
		"name": "None"
	},
	"initiallyHidden": false,
	"completionRewardsIds": [],
	"completionQuantity": 1,
	"minimumRequirement": true,
	"completionFlags": [
		"FoundDiaryPage15"
	],
	"instanceCompletionResult": [],
	"enabledPredicate":
	{
		"expression": ""
	},
	"completionActionsIds": [],
	"allowMultipleCompletion": false,
	"maximumAdditionalCompletions": 100,
	"multipleCompletionExperienceMultiplier": 0.30000001192092896,
	"multipleCompletionGoldMultiplier": 0.30000001192092896,
	"multipleCompletionVariableMultiplier": 0.30000001192092896,
	"objectiveName": "NSLOCTEXT(\"\", \"4B92C72E405BC26CE45688853F530ACF\", \"Find Roderic\\'s diary\\'s missing page 15\")",
	"killObjectiveTagContainer":
	{
		"gameplayTags": [],
		"parentTags": []
	},
	"collectionFilterId":
	{
		"guid": "0",
		"typeId": "1091110041",
		"name": "None"
	},
	"collectionCount": 5,
	"bConsumeItems": true,
	"displayLocation": [],
	"location": [],
	"guid": "6064628945739251717",
	"name": "MAO_0012_RWS_FindDiaryPage15",
	"typeId": "1091110036"
}